{
    "posts": [
        {
            "createtime": "2016-07-21T12:44:56+08:00", 
            "image": null, 
            "link": "http://www.jianshu.com/p/f30cab76d378", 
            "title": "CSS Loading 纯css"
        }, 
        {
            "createtime": "2016-07-05T17:38:38+08:00", 
            "image": "http://upload-images.jianshu.io/upload_images/144590-ea89c4d457c5ab94.jpg?imageMogr2/auto-orient/strip%7CimageView2/1/w/300/h/300", 
            "link": "http://www.jianshu.com/p/49e43d40662e", 
            "title": "高德地图SDK-iOS"
        }, 
        {
            "createtime": "2016-06-13T16:35:08+08:00", 
            "image": "http://upload-images.jianshu.io/upload_images/144590-88c6e8efe0fff05e.jpeg?imageMogr2/auto-orient/strip%7CimageView2/1/w/300/h/300", 
            "link": "http://www.jianshu.com/p/b8a4576260bc", 
            "title": "无线端规划"
        }, 
        {
            "createtime": "2016-05-31T11:42:49+08:00", 
            "image": "http://upload-images.jianshu.io/upload_images/144590-6db3066db1669583.png?imageMogr2/auto-orient/strip%7CimageView2/1/w/300/h/300", 
            "link": "http://www.jianshu.com/p/a6b00872e719", 
            "title": "LRU?"
        }, 
        {
            "createtime": "2016-05-15T13:11:20+08:00", 
            "image": null, 
            "link": "http://www.jianshu.com/p/82bc161102b5", 
            "title": "Reader Submissions New Year's 2016"
        }, 
        {
            "createtime": "2016-05-15T13:00:33+08:00", 
            "image": null, 
            "link": "http://www.jianshu.com/p/3116c89f13f1", 
            "title": "UIText​Checker"
        }, 
        {
            "createtime": "2016-04-29T16:44:17+08:00", 
            "image": "http://upload-images.jianshu.io/upload_images/144590-aa0cbcd8ffe3202d.png?imageMogr2/auto-orient/strip%7CimageView2/1/w/300/h/300", 
            "link": "http://www.jianshu.com/p/d395d1ced4e1", 
            "title": "ASyncDisplayKitDemo"
        }, 
        {
            "createtime": "2016-04-20T10:40:49+08:00", 
            "image": "http://upload-images.jianshu.io/upload_images/144590-e30f61b05a664e9c.jpg?imageMogr2/auto-orient/strip%7CimageView2/1/w/300/h/300", 
            "link": "http://www.jianshu.com/p/95f32fbb9e17", 
            "title": "破解iPhone很难么? FBI教你如何破iPhone"
        }, 
        {
            "createtime": "2016-04-19T13:17:43+08:00", 
            "image": null, 
            "link": "http://www.jianshu.com/p/26a0eb697e3c", 
            "title": "阅读才能让你快速`增肥`"
        }
    ], 
    "updated_at": "2016-08-02T09:17:31.127914"
}